README.md
setup.py
examples/__init__.py
examples/django_example.py
examples/flask_example.py
examples/general_example.py
examples/repo.py
examples/sanic_example.py
pythondi/__init__.py
pythondi/container.py
pythondi/exceptions.py
pythondi/provider.py
pythondi.egg-info/PKG-INFO
pythondi.egg-info/SOURCES.txt
pythondi.egg-info/dependency_links.txt
pythondi.egg-info/top_level.txt
tests/__init__.py
tests/test_configure.py
tests/test_container.py
tests/test_inject.py
tests/test_provider.py