Metadata-Version: 2.1
Name: pythondi
Version: 1.2.4
Summary: Python dependency injection library
Home-page: https://github.com/teamhide/pythondi
Author: Hide
Author-email: padocon@naver.com
License: UNKNOWN
Platform: UNKNOWN
Classifier: Intended Audience :: Developers
Classifier: Programming Language :: Python
Classifier: Programming Language :: Python :: 3.5
Classifier: Programming Language :: Python :: 3.6
Classifier: Programming Language :: Python :: 3.7
Classifier: Programming Language :: Python :: 3.8
Classifier: License :: OSI Approved :: Apache Software License
Classifier: Operating System :: OS Independent
Requires-Python: >=3.5
